{"data":{"allStrapiJobs":{"nodes":[{"position":"Javascript developer","company":"Freelance","date":"April 2020","description":[{"id":4,"name":"Develop and create UI/UX designs"},{"id":5,"name":"Make HTML/CSS/JS layouts"},{"id":6,"name":"Develop server-side on Node JS"}],"strapiId":2},{"position":"Technical translator","company":"BitDegree","date":"February 2019 - March 2020","description":[{"id":10,"name":"Created programming tutorials"},{"id":11,"name":"Created images/designs"}],"strapiId":4}]}}}